sbom.xml
nvd_api/__init__.py
nvd_api/client.py
nvd_api/low_api/__init__.py
nvd_api/low_api/api/__init__.py
nvd_api/low_api/api/products_api.py
nvd_api/low_api/api/vulnerabilities_api.py
nvd_api/low_api/api_client.py
nvd_api/low_api/apis/__init__.py
nvd_api/low_api/configuration.py
nvd_api/low_api/exceptions.py
nvd_api/low_api/model/__init__.py
nvd_api/low_api/model/cpe_match_oas.py
nvd_api/low_api/model/cpe_match_oas_match_strings_inner.py
nvd_api/low_api/model/cpe_match_oas_match_strings_inner_match_string.py
nvd_api/low_api/model/cpe_match_oas_match_strings_inner_match_string_matches_inner.py
nvd_api/low_api/model/cpe_oas.py
nvd_api/low_api/model/cpe_oas_products_inner.py
nvd_api/low_api/model/cpe_oas_products_inner_cpe.py
nvd_api/low_api/model/cpe_oas_products_inner_cpe_deprecated_by_inner.py
nvd_api/low_api/model/cpe_oas_products_inner_cpe_refs_inner.py
nvd_api/low_api/model/cpe_oas_products_inner_cpe_titles_inner.py
nvd_api/low_api/model/cve_history_oas.py
nvd_api/low_api/model/cve_history_oas_cve_changes_inner.py
nvd_api/low_api/model/cve_history_oas_cve_changes_inner_change.py
nvd_api/low_api/model/cve_history_oas_cve_changes_inner_change_details_inner.py
nvd_api/low_api/model/cve_oas.py
nvd_api/low_api/model/cve_oas_vulnerabilities_inner.py
nvd_api/low_api/model/cve_oas_vulnerabilities_inner_cve.py
nvd_api/low_api/model/cve_oas_vulnerabilities_inner_cve_configurations_inner.py
nvd_api/low_api/model/cve_oas_vulnerabilities_inner_cve_configurations_inner_nodes_inner.py
nvd_api/low_api/model/cve_oas_vulnerabilities_inner_cve_configurations_inner_nodes_inner_cpe_match_inner.py
nvd_api/low_api/model/cve_oas_vulnerabilities_inner_cve_descriptions_inner.py
nvd_api/low_api/model/cve_oas_vulnerabilities_inner_cve_metrics.py
nvd_api/low_api/model/cve_oas_vulnerabilities_inner_cve_metrics_cvss_metric_v2_inner.py
nvd_api/low_api/model/cve_oas_vulnerabilities_inner_cve_metrics_cvss_metric_v30_inner.py
nvd_api-0.9.0.dist-info/entry_points.txt
nvd_api-0.9.0.dist-info/LICENSE
nvd_api-0.9.0.dist-info/WHEEL
nvd_api-0.9.0.dist-info/METADATA
nvd_api-0.9.0.dist-info/RECORD
